<annotation>
	<folder>children</folder>
	<filename>child12.jpg</filename>
	<path>C:\Users\bazariann\Downloads\children-20220603T194303Z-001\children\child12.jpg</path>
	<source>
		<database>Unknown</database>
	</source>
	<size>
		<width>2120</width>
		<height>1414</height>
		<depth>3</depth>
	</size>
	<segmented>0</segmented>
	<object>
		<name>human</name>
		<pose>Unspecified</pose>
		<truncated>1</truncated>
		<difficult>0</difficult>
		<bndbox>
			<xmin>1077</xmin>
			<ymin>111</ymin>
			<xmax>1857</xmax>
			<ymax>1414</ymax>
		</bndbox>
	</object>
	<object>
		<name>human</name>
		<pose>Unspecified</pose>
		<truncated>1</truncated>
		<difficult>0</difficult>
		<bndbox>
			<xmin>1626</xmin>
			<ymin>112</ymin>
			<xmax>2120</xmax>
			<ymax>1414</ymax>
		</bndbox>
	</object>
	<object>
		<name>human</name>
		<pose>Unspecified</pose>
		<truncated>0</truncated>
		<difficult>0</difficult>
		<bndbox>
			<xmin>620</xmin>
			<ymin>37</ymin>
			<xmax>1089</xmax>
			<ymax>778</ymax>
		</bndbox>
	</object>
</annotation>
