<annotation>
	<folder>nepalese people</folder>
	<filename>nepalese23.jpg</filename>
	<path>C:\Users\bazariann\Downloads\nepalese people-20220603T203143Z-001\nepalese people\nepalese23.jpg</path>
	<source>
		<database>Unknown</database>
	</source>
	<size>
		<width>3888</width>
		<height>2592</height>
		<depth>3</depth>
	</size>
	<segmented>0</segmented>
	<object>
		<name>human</name>
		<pose>Unspecified</pose>
		<truncated>1</truncated>
		<difficult>0</difficult>
		<bndbox>
			<xmin>48</xmin>
			<ymin>333</ymin>
			<xmax>1709</xmax>
			<ymax>2592</ymax>
		</bndbox>
	</object>
	<object>
		<name>human</name>
		<pose>Unspecified</pose>
		<truncated>1</truncated>
		<difficult>0</difficult>
		<bndbox>
			<xmin>1493</xmin>
			<ymin>311</ymin>
			<xmax>3274</xmax>
			<ymax>2592</ymax>
		</bndbox>
	</object>
</annotation>
