<annotation>
	<folder>train</folder>
	<filename>beagle40.jpg</filename>
	<path>C:\Users\bazariann\Downloads\train\beagle40.jpg</path>
	<source>
		<database>Unknown</database>
	</source>
	<size>
		<width>602</width>
		<height>1070</height>
		<depth>3</depth>
	</size>
	<segmented>0</segmented>
	<object>
		<name>dog</name>
		<pose>Unspecified</pose>
		<truncated>1</truncated>
		<difficult>0</difficult>
		<bndbox>
			<xmin>1</xmin>
			<ymin>215</ymin>
			<xmax>532</xmax>
			<ymax>1007</ymax>
		</bndbox>
	</object>
</annotation>
